tests/__init__.py
tests/test_urlbox_client.py
tests/test_webhook_validator.py
urlbox/__init__.py
urlbox/invalid_header_signature_error.py
urlbox/invalid_url_exception.py
urlbox/urlbox_client.py
urlbox/webhook_validator.py
urlbox-1.0.6.dist-info/LICENSE.txt
urlbox-1.0.6.dist-info/METADATA
urlbox-1.0.6.dist-info/WHEEL
urlbox-1.0.6.dist-info/top_level.txt
urlbox-1.0.6.dist-info/RECORD
