Metadata-Version: 2.1
Name: urlbox
Version: 1.0.6
Summary: Official Python client for the Ulrbox API
Home-page: https://github.com/urlbox/urlbox-python
Author: Urlbox
Author-email: support@urlbox.io
License: MIT
Project-URL: Bug Tracker, https://github.com/urlbox/urlbox-python/issues
Platform: UNKNOWN
Classifier: Programming Language :: Python :: 3
Classifier: License :: OSI Approved :: MIT License
Classifier: Operating System :: OS Independent
Requires-Python: >=3.7
License-File: LICENSE.txt
